.gitignore
.readthedocs.yml
.travis.yml
AUTHORS.rst
CHANGELOG.rst
LICENSE.txt
README.md
autobuild_docs.py
pyproject.toml
setup.cfg
setup.py
tox.ini
docker_images/mbf_anysnake_18.04/Dockerfile
docker_images/mbf_anysnake_18.04/build.sh
docker_images/mbf_anysnake_18.04/sudoers
docs/Makefile
docs/authors.rst
docs/changelog.rst
docs/conf.py
docs/index.rst
docs/license.rst
docs/requirements.txt
docs/_static/.gitignore
docs/_static/index.png
docs/_static/my-styles.css
src/mbf_anysnake/__init__.py
src/mbf_anysnake/_inside_dockfill_bioconductor.py
src/mbf_anysnake/anysnake.py
src/mbf_anysnake/cli.py
src/mbf_anysnake/dockfill_bioconductor.py
src/mbf_anysnake/dockfill_docker.py
src/mbf_anysnake/dockfill_python.py
src/mbf_anysnake/dockfill_r.py
src/mbf_anysnake/dockfill_rust.py
src/mbf_anysnake/parser.py
src/mbf_anysnake/testing.py
src/mbf_anysnake/util.py
src/mbf_anysnake.egg-info/PKG-INFO
src/mbf_anysnake.egg-info/SOURCES.txt
src/mbf_anysnake.egg-info/dependency_links.txt
src/mbf_anysnake.egg-info/entry_points.txt
src/mbf_anysnake.egg-info/not-zip-safe
src/mbf_anysnake.egg-info/requires.txt
src/mbf_anysnake.egg-info/top_level.txt
tests/conftest.py
tests/test_flake8.py