Metadata-Version: 2.1
Name: mbf-anysnake
Version: 0.2
Summary: wrappers for docker+python+R+bioconductor
Home-page: https://github.com/TyberiusPrime/mbf_anysnake
Author: Florian Finkernagel
Author-email: finkernagel@imt.uni-marburg.de
License: mit
Platform: any
Classifier: Development Status :: 4 - Beta
Classifier: Programming Language :: Python
Requires-Python: >=3.5
Provides-Extra: doc
Provides-Extra: testing
